hiptest/__init__.py
hiptest/client.py
python_hiptest-0.0.0.dist-info/METADATA
python_hiptest-0.0.0.dist-info/RECORD
python_hiptest-0.0.0.dist-info/WHEEL
python_hiptest-0.0.0.dist-info/top_level.txt
