Metadata-Version: 2.1
Name: python-hiptest
Version: 0.0.0
Summary: Unofficial python API client for Hiptest
Home-page: https://github.com/jlane9/python-hiptest
Author: jlane
Author-email: jlane@fanthreesixty.com
License: MIT
Keywords: hiptest qa testing bdd api
Platform: UNKNOWN
Classifier: Development Status :: 4 - Beta
Classifier: Framework :: Pytest
Classifier: Intended Audience :: Developers
Classifier: Operating System :: POSIX
Classifier: Operating System :: Microsoft :: Windows
Classifier: Operating System :: MacOS :: MacOS X
Classifier: Topic :: Software Development :: Testing
Classifier: Topic :: Software Development :: Quality Assurance
Classifier: Topic :: Software Development :: Libraries
Classifier: Topic :: Utilities
Classifier: Programming Language :: Python :: 2.7
Classifier: Programming Language :: Python :: 3.5
Classifier: Programming Language :: Python :: 3.6
